<?xml version="1.0" encoding="UTF-8"?>
<sconti xmlns:xsi="http://www.w3.org/2001/XMLSchema-instance" xsi:noNamespaceSchemaLocation="sconti.xsd">
  <sconto id="7">
    <id_prodotto>2</id_prodotto>
    <id_prodotto>3</id_prodotto>
    <id_prodotto>4</id_prodotto>
    <id_prodotto>5</id_prodotto>
    <id_prodotto>6</id_prodotto>
    <id_prodotto>7</id_prodotto>
    <id_prodotto>8</id_prodotto>
    <id_prodotto>9</id_prodotto>
    <id_prodotto>10</id_prodotto>
    <id_prodotto>11</id_prodotto>
    <condizione tipo="offerta_speciale">
      <evento>Black Friday</evento>
    </condizione>
    <percentuale>5</percentuale>
    <data_inizio>2025-10-20</data_inizio>
    <data_fine>2025-10-26</data_fine>
    <destinatari>
      <id_utente>4</id_utente>
      <id_utente>5</id_utente>
    </destinatari>
  </sconto>
  <sconto id="8">
    <id_prodotto>1</id_prodotto>
    <condizione tipo="crediti_da_data">
      <valore>50</valore>
      <data_riferimento>2025-10-25</data_riferimento>
    </condizione>
    <percentuale>30</percentuale>
    <data_inizio>2025-10-13</data_inizio>
    <data_fine>2025-10-26</data_fine>
    <destinatari>
      <id_utente>4</id_utente>
      <id_utente>5</id_utente>
    </destinatari>
  </sconto>
</sconti>
